Metadata-Version: 1.1
Name: launch
Version: 0.1.3
Summary: Launch: An Application Launcher
Home-page: https://bitbucket.org/flowdas/launch
Author: Flowdas Inc.
Author-email: prospero@flowdas.com
License: MPL 2.0
Keywords: cli,configuration,plugin
Platform: UNKNOWN
Classifier: Development Status :: 5 - Production/Stable
Classifier: Environment :: Console
Classifier: Environment :: Plugins
Classifier: Intended Audience :: Developers
Classifier: License :: OSI Approved :: Mozilla Public License 2.0 (MPL 2.0)
Classifier: Operating System :: MacOS :: MacOS X
Classifier: Operating System :: POSIX
Classifier: Programming Language :: Python
Classifier: Programming Language :: Python :: 2
Classifier: Programming Language :: Python :: 2.7
Classifier: Programming Language :: Python :: 3
Classifier: Programming Language :: Python :: 3.5
Classifier: Programming Language :: Python :: 3.6
